CHANGELOG.md
LICENSE
MANIFEST.in
Makefile
README.md
setup.cfg
setup.py
tox.ini
wc_django_locales_collector.egg-info/PKG-INFO
wc_django_locales_collector.egg-info/SOURCES.txt
wc_django_locales_collector.egg-info/dependency_links.txt
wc_django_locales_collector.egg-info/requires.txt
wc_django_locales_collector.egg-info/top_level.txt
wcd_locales_collector/__init__.py
wcd_locales_collector/apps.py
wcd_locales_collector/conf.py
wcd_locales_collector/discovery.py
wcd_locales_collector/helpers.py
wcd_locales_collector/management/__init__.py
wcd_locales_collector/management/commands/__init__.py
wcd_locales_collector/management/commands/collectlocales.py
wcd_locales_collector/services/__init__.py
wcd_locales_collector/services/collector.py
wcd_locales_collector/services/pathifier.py